accountifie/__init__.py
accountifie/urls.py
accountifie/address/__init__.py
accountifie/address/admin.py
accountifie/address/models.py
accountifie/address/migrations/0001_initial.py
accountifie/address/migrations/__init__.py
accountifie/cal/__init__.py
accountifie/cal/admin.py
accountifie/cal/models.py
accountifie/cal/tests.py
accountifie/cal/views.py
accountifie/cal/management/__init__.py
accountifie/cal/management/commands/__init__.py
accountifie/cal/management/commands/populate_calendar.py
accountifie/cal/migrations/0001_initial.py
accountifie/cal/migrations/__init__.py
accountifie/celery/__init__.py
accountifie/celery/admin.py
accountifie/celery/apiv1.py
accountifie/celery/celery_main.py
accountifie/celery/serializers.py
accountifie/celery/urls.py
accountifie/celery/views.py
accountifie/common/__init__.py
accountifie/common/admin.py
accountifie/common/api.py
accountifie/common/auth_urls.py
accountifie/common/db.py
accountifie/common/dbutils.py
accountifie/common/forms.py
accountifie/common/log.py
accountifie/common/models.py
accountifie/common/serializers.py
accountifie/common/table.py
accountifie/common/urls.py
accountifie/common/views.py
accountifie/common/apiv1/__init__.py
accountifie/common/apiv1/server_info.py
accountifie/common/migrations/0001_initial.py
accountifie/common/migrations/0002_address.py
accountifie/common/migrations/0003_address_label.py
accountifie/common/migrations/__init__.py
accountifie/common/static/__init__.py
accountifie/common/static/common/angularjs/css/xeditable.css
accountifie/common/static/common/angularjs/js/angular-cookies.js
accountifie/common/static/common/angularjs/js/angular-cookies.min.js
accountifie/common/static/common/angularjs/js/angular-cookies.min.js.map
accountifie/common/static/common/angularjs/js/angular.js
accountifie/common/static/common/angularjs/js/angular.min.js
accountifie/common/static/common/angularjs/js/angular.min.js.map
accountifie-0.0.0.dist-info/DESCRIPTION.rst
accountifie-0.0.0.dist-info/METADATA
accountifie-0.0.0.dist-info/RECORD
accountifie-0.0.0.dist-info/WHEEL
accountifie-0.0.0.dist-info/metadata.json
accountifie-0.0.0.dist-info/top_level.txt
