Metadata-Version: 2.0
Name: accountifie
Version: 0.0.0
Summary: Core Accouting Functionality
Home-page: https://github.com/electronifie/accountifie
Author: Ian McAllister
Author-email: ian.mcallister@electronifie.com
License: UNKNOWN
Platform: UNKNOWN
